ecmwf/datastores/__init__.py
ecmwf/datastores/catalogue.py
ecmwf/datastores/client.py
ecmwf/datastores/config.py
ecmwf/datastores/legacy_client.py
ecmwf/datastores/processing.py
ecmwf/datastores/profile.py
ecmwf/datastores/py.typed
ecmwf/datastores/utils.py
ecmwf/datastores/version.py
ecmwf_datastores_client-0.3.0.dist-info/licenses/LICENSE
ecmwf_datastores_client-0.3.0.dist-info/METADATA
ecmwf_datastores_client-0.3.0.dist-info/WHEEL
ecmwf_datastores_client-0.3.0.dist-info/top_level.txt
ecmwf_datastores_client-0.3.0.dist-info/RECORD
