Metadata-Version: 2.4
Name: ecmwf-datastores-client
Version: 0.3.0
Summary: ECMWF Data Stores Service (DSS) API Python client
License:                                  Apache License
Project-URL: documentation, https://ecmwf.github.io/ecmwf-datastores-client/
Project-URL: source, https://github.com/ecmwf/ecmwf-datastores-client
Project-URL: tracker, https://github.com/ecmwf/ecmwf-datastores-client/issues
Classifier: Development Status :: 2 - Pre-Alpha
Classifier: Intended Audience :: Science/Research
Classifier: License :: OSI Approved :: Apache Software License
Classifier: Operating System :: OS Independent
Classifier: Programming Language :: Python
Classifier: Programming Language :: Python :: 3
Classifier: Programming Language :: Python :: 3.8
Classifier: Programming Language :: Python :: 3.9
Classifier: Programming Language :: Python :: 3.10
Classifier: Programming Language :: Python :: 3.11
Classifier: Programming Language :: Python :: 3.12
Classifier: Programming Language :: Python :: 3.13
Classifier: Topic :: Scientific/Engineering
Requires-Python: >=3.8
License-File: LICENSE
Requires-Dist: attrs
Requires-Dist: multiurl>=0.3.2
Requires-Dist: requests
Requires-Dist: typing-extensions
Provides-Extra: legacy
Requires-Dist: cdsapi>=0.7.6; extra == "legacy"
Dynamic: license-file
